Workbook

Sheet Preços dos Materiais
A1: Material / Serviço | B1: Especificação / Modelo | C1: Unidade Comercial | D1: Preço de Custo Cheio (R$)
A2: MDF | B2: Preto | C2: Chapa (2.75x1.84m) | D2: 250
A3: MDF | B3: Branco | C3: Chapa (2.75x1.84m) | D3: 210
A4: MDF | B4: Cinza | C4: Chapa (2.75x1.84m) | D4: 240
A5: MDF | B5: Louro Freijó | C5: Chapa (2.75x1.84m) | D5: 310
A6: Fita de Borda | B6: Preto | C6: Rolo (20 metros) | D6: 45
A7: Fita de Borda | B7: Branco | C7: Rolo (20 metros) | D7: 35
A8: Fita de Borda | B8: Cinza | C8: Rolo (20 metros) | D8: 40
A9: Fita de Borda | B9: Louro Freijó | C9: Rolo (20 metros) | D9: 55
A10: Metalon Ferro | B10: 15x15 Chapa 18 | C10: Barra (6 metros) | D10: 45
A11: Metalon Ferro | B11: 15x15 Chapa 20 | C11: Barra (6 metros) | D11: 38
A12: Metalon Ferro | B12: 20x20 Chapa 18 | C12: Barra (6 metros) | D12: 55
A13: Metalon Ferro | B13: 20x20 Chapa 20 | C13: Barra (6 metros) | D13: 48
... A49: Insumo Oficina | B49: Insumos Polimento | C49: Peça | D49: 12

Sheet Móveis Industriais
A1: ORÇAMENTO DE MÓVEIS INDUSTRIAIS (CONFORME FOTO)
A3: MEDIDAS DA MESA (Em metros)
A4: Comprimento: | B4: 1.5 | D4: Cor do MDF desejada: | E4: Louro Freijó
A5: Largura: | B5: 0.8 | D5: Modelo Metalon desejado: | E5: 30x40 Chapa 18
A6: Altura: | B6: 0.75 | D6: Margem de Lucro Desejada: | E6: 0.5
A9: Insumo / Componente | B9: Fórmula Comercial Proporcional | C9: Quantidade Usada | D9: Preço Un. Cheio (R$) | E9: Subtotal (R$)
A10: Tampo MDF | B10: Área da mesa / Área da Chapa (5.06 m²) | C10: =(B4*B5)/5.06 | D10: =VLOOKUP(E4, 'Preços dos Materiais'!B2:D50, 2, FALSE) | E10: =C10*D10
A11: Fita de Borda | B11: Perímetro do tampo / Rolo de 20 metros | C11: =((B4+B5)*2)/20 | D11: =VLOOKUP(E4, 'Preços dos Materiais'!B6:D50, 2, FALSE) | E11: =C11*D11
A12: Estrutura Metalon Ferro | B12: 4 Pernas + 4 Travas Laterais + 2 Travas Longas (Foto) | C12: =((B6*4)+(B5*4)+(B4*2))/6 | D12: =VLOOKUP(E5, 'Preços dos Materiais'!B2:D50, 2, FALSE) | E12: =C12*D12
A13: Pés de Regulagem Niveladores | B13: Fixo 4 unidades rosqueadas por mesa (Foto) | C13: 4 | D13: =VLOOKUP("Pé de Regulagem Mesa", 'Preços dos Materiais'!B2:D50, 2, FALSE) | E13: =C13*D13
A14: Parafusos de Fixação | B14: Fração média estimada por tampo preso | C14: 0.2 | D14: =VLOOKUP("Parafusos Caixa", 'Preços dos Materiais'!B2:D50, 2, FALSE) | E14: =C14*D14
A15: Disco de Corte | B15: Gasto médio por cortes da estrutura | C15: 1 | D15: =VLOOKUP("Disco de Corte", 'Preços dos Materiais'!B2:D50, 2, FALSE) | E15: =C15*D15
A16: Disco Flap | B16: Gasto médio para acabamento e desbaste | C16: 0.5 | D16: =VLOOKUP("Disco Flap", 'Preços dos Materiais'!B2:D50, 2, FALSE) | E16: =C16*D16
A17: Insumo de Solda | B17: Gasto médio fixado por estrutura soldada | C17: 1 | D17: =VLOOKUP("Solda (Eletrodo/MIG)", 'Preços dos Materiais'!B2:D50, 2, FALSE) | E17: =C17*D17
A18: Pintura da Estrutura | B18: Gasto fixado por fundo protetor e acabamento | C18: 1 | D18: =VLOOKUP("Pintura Estrutura", 'Preços dos Materiais'!B2:D50, 2, FALSE) | E18: =C18*D18
D20: CUSTO TOTAL DA MATÉRIA-PRIMA: | E20: =SUM(E10:E18)
D21: PREÇO DE VENDA SUGERIDO: | E21: =E20/(1-E6)

Sheet Bancadas Inox
A1: ORÇAMENTO DE BANCADAS EM AÇO INOXIDÁVEL
A3: MEDIDAS DA BANCADA (Em metros)
A4: Comprimento: | B4: 2 | D4: Modelo (1 = Bancada Dupla | 2 = Simples Gradeada): | E4: 1
A5: Largura: | B5: 0.7 | D5: Chapa de Inox Escolhida: | E5: 3.00x1.25m Ch18
A6: Altura: | B6: 0.85 | D6: Modelo do Tubo Inox (Pés): | E6: 1.1/2" Chapa 18
D7: Margem de Lucro Desejada: | E7: 0.5
A10: Insumo / Componente | B10: Fórmula de Proporção e Desgaste | C10: Quantidade Usada | D10: Preço Un. Cheio (R$) | E10: Subtotal (R$)
A11: Chapa de Aço Inox | B11: Área total / Área chapa comercial (3.75 m²) | C11: =IF(E4=1, ((B4*B5)/3.75)*2, (B4*B5)/3.75) | D11: =VLOOKUP(E5, 'Preços dos Materiais'!B2:D50, 2, FALSE) | E11: =C11*D11
A12: Serviço de Dobra Terceirizado | B12: Perímetro linear de dobras totais por metro | C12: =IF(E4=1, ((B4+B5)*2)*2, (B4+B5)*2) | D12: =VLOOKUP("Dobra de Chapa Inox", 'Preços dos Materiais'!B2:D50, 2, FALSE) | E12: =C12*D12
A13: Estrutura e Gradeado (Tubos) | B13: Cálculo dos 4 pés + travamentos + grade inferior | C13: =IF(E4=1, ((B6*4)+(B4*4)+(B5*4))/6, ((B6*4)+(B4*4)+(B5*4)+(B4*3))/6) | D13: =VLOOKUP(E6, 'Preços dos Materiais'!B2:D50, 2, FALSE) | E13: =C13*D13
A14: Borrachas de Vedação Pés | B14: Fixo 4 ponteiras de borracha protetora por bancada | C14: 4 | D14: =VLOOKUP("Borracha para Pés", 'Preços dos Materiais'!B2:D50, 2, FALSE) | E14: =C14*D14
A15: Solda TIG + Gás Argônio | B15: Insumos e consumo de fixação de inox | C15: 1 | D15: =VLOOKUP("Solda TIG + Argônio", 'Preços dos Materiais'!B2:D50, 2, FALSE) | E15: =C15*D15
A16: Insumos de Polimento | B16: Massas de polir e discos de feltro de acabamento | C16: 1 | D16: =VLOOKUP("Insumos Polimento", 'Preços dos Materiais'!B2:D50, 2, FALSE) | E16: =C16*D16
D18: CUSTO TOTAL DA BANCADA: | E18: =SUM(E11:E16)
D19: PREÇO DE VENDA SUGERIDO: | E19: =E18/(1-E7)

Sheet Barras de Apoio Inox
A1: ORÇAMENTO DE BARRAS DE APOIO POR TAMANHO REAL
A3: DIGITE AS MEDIDAS DA PEÇA (Em metros)
A4: Modelo (1 = Barra Reta | 2 = Em L Parede ao Chão): | B4: 2
A5: Comprimento (Avanço na Parede): | B5: 0.7
A6: Altura (Descida até o Chão - se houver): | B6: 0.75
A7: Margem de Lucro Desejada: | B7: 0.5
A10: Insumo / Componente | B10: Especificação Técnica de Fábrica | C10: Quantidade Usada | D10: Preço Un. Cheio (R$) | E10: Subtotal (R$)
A11: Tubo Inox 1.1/4" 304 Ch18 | B11: Metragem total somada / Barra de 6 metros | C11: =IF(B4=1, B5/6, (B5+B6)/6) | D11: =VLOOKUP("1.1/4"" 304 Ch18", 'Preços dos Materiais'!B2:D50, 2, FALSE) | E11: =C11*D11
A12: Curva de 90° 1.1/4" | B12: Adiciona 1 unidade automática para junção de canto | C12: =IF(B4=1, 0, 1) | D12: =VLOOKUP("Curva 90° 1.1/4""", 'Preços dos Materiais'!B2:D50, 2, FALSE) | E12: =C12*D12
A13: Flanges de Fixação | B13: Fixo 2 flanges de fixação estrutural reforçada | C13: 2 | D13: =VLOOKUP("Flange 1.1/4""", 'Preços dos Materiais'!B2:D50, 2, FALSE) | E13: =C13*D13
A14: Canoplas de Acabamento | B14: Fixo 2 canoplas de cobertura protetora de parafusos | C14: 2 | D14: =VLOOKUP("Canopla 1.1/4""", 'Preços dos Materiais'!B2:D50, 2, FALSE) | E14: =C14*D14
A15: Solda TIG + Gás Argônio | B15: Fração de insumos e tratamento de emendas | C15: 0.5 | D15: =VLOOKUP("Solda TIG + Argônio", 'Preços dos Materiais'!B2:D50, 2, FALSE) | E15: =C15*D15
A16: Insumos de Polimento | B16: Gasto médio para acabamento alto brilho/escovado | C16: 0.5 | D16: =VLOOKUP("Insumos Polimento", 'Preços dos Materiais'!B2:D50, 2, FALSE) | E16: =C16*D16
D18: CUSTO TOTAL DA BARRA: | E18: =SUM(E11:E16)
D19: PREÇO DE VENDA SUGERIDO: | E19: =E18/(1-B7)
